epab/__init__.py
epab/__main__.py
epab/_logging.py
epab/exc.py
epab/bases/__init__.py
epab/bases/repo.py
epab/cmd/__init__.py
epab/cmd/_chglog.py
epab/cmd/_compile_qt.py
epab/cmd/_doc.py
epab/cmd/_freeze.py
epab/cmd/_graph.py
epab/cmd/_install_hooks.py
epab/cmd/_next_version.py
epab/cmd/_pipenv.py
epab/cmd/_print_version.py
epab/cmd/_push.py
epab/cmd/_pytest.py
epab/cmd/_release.py
epab/cmd/_reqs.py
epab/core/__init__.py
epab/core/config.py
epab/core/context.py
epab/linters/__init__.py
epab/linters/_bandit.py
epab/linters/_dead_fixtures.py
epab/linters/_flake8.py
epab/linters/_lint.py
epab/linters/_mypy.py
epab/linters/_pep8.py
epab/linters/_pylint.py
epab/linters/_safety.py
epab/linters/_sort.py
epab/utils/__init__.py
epab/utils/_av.py
epab/utils/_ensure_exe.py
epab/utils/_exe_version.py
epab/utils/_gitignore.py
epab/utils/_next_version.py
epab/utils/_repo.py
epab/utils/_resource_path.py
epab/utils/_run_once.py
epab/utils/_stashed.py
epab/utils/_timeit.py
epab/vendor/app.ico
epab/vendor/verpatch.exe
test/__init__.py
test/conftest.py
test/test_imports.py
test/test_main.py
test/test_cmd/test_changelog.py
test/test_cmd/test_compile_qt_resources.py
test/test_cmd/test_freeze.py
test/test_cmd/test_git_hooks.py
test/test_cmd/test_linters.py
test/test_cmd/test_push.py
test/test_cmd/test_release.py
test/test_cmd/test_requirements.py
test/test_cmd/test_test_runner.py
test/test_files/missing_attrib.exe
test/test_files/no_version.exe
test/test_files/version_ok.exe
test/test_repo/conftest.py
test/test_repo/test_branch.py
test/test_repo/test_checkout.py
test/test_repo/test_commit.py
test/test_repo/test_index.py
test/test_repo/test_merge.py
test/test_repo/test_repo.py
test/test_repo/test_stash.py
test/test_repo/test_tag.py
test/test_utils/test_av.py
test/test_utils/test_exe_version.py
test/test_utils/test_resource_path.py
test/test_utils/test_next_version/conftest.py
test/test_utils/test_next_version/test_calver.py
EPAB-2018.12.18.1.dist-info/LICENSE
EPAB-2018.12.18.1.dist-info/METADATA
EPAB-2018.12.18.1.dist-info/WHEEL
EPAB-2018.12.18.1.dist-info/entry_points.txt
EPAB-2018.12.18.1.dist-info/top_level.txt
EPAB-2018.12.18.1.dist-info/RECORD
