Metadata-Version: 2.1
Name: EPAB
Version: 2018.12.18.1
Summary: Etcher's Python Application Builder
Home-page: https://github.com/132nd-etcher/EPAB
Author: 132nd-etcher
Author-email: epab@daribouca.net
License: GPLv3
Download-URL: https://github.com/132nd-etcher/EPAB/releases
Platform: win32
Classifier: Development Status :: 3 - Alpha
Classifier: Topic :: Utilities
Classifier: License :: OSI Approved :: MIT License
Classifier: Environment :: Win32 (MS Windows)
Classifier: Natural Language :: English
Classifier: Operating System :: Microsoft :: Windows
Classifier: Operating System :: Microsoft :: Windows :: Windows 7
Classifier: Operating System :: Microsoft :: Windows :: Windows 8
Classifier: Operating System :: Microsoft :: Windows :: Windows 8.1
Classifier: Operating System :: Microsoft :: Windows :: Windows 10
Classifier: Programming Language :: Cython
Classifier: Programming Language :: Python
Classifier: Programming Language :: Python :: 3 :: Only
Classifier: Programming Language :: Python :: 3.6
Classifier: Programming Language :: Python :: Implementation
Classifier: Programming Language :: Python :: Implementation :: CPython
Classifier: Topic :: Games/Entertainment
Classifier: Topic :: Utilities
Requires-Python: >=3.6
Requires-Dist: click
Requires-Dist: wheel
Requires-Dist: twine
Requires-Dist: pylint
Requires-Dist: isort
Requires-Dist: safety
Requires-Dist: flake8
Requires-Dist: coverage
Requires-Dist: hypothesis
Requires-Dist: pytest-cache
Requires-Dist: pytest-cov
Requires-Dist: pytest-vcr
Requires-Dist: pytest-pycharm
Requires-Dist: pytest
Requires-Dist: gitchangelog
Requires-Dist: gitpython
Requires-Dist: mockito
Requires-Dist: setuptools-scm
Requires-Dist: certifi
Requires-Dist: pefile
Requires-Dist: mypy
Requires-Dist: toml
Requires-Dist: sarge
Requires-Dist: pytest-repeat
Requires-Dist: pytest-faker
Requires-Dist: pytest-watch
Requires-Dist: pytest-deadfixtures
Requires-Dist: bandit
Requires-Dist: elib-config
Requires-Dist: elib-run
Requires-Dist: pystache
